dreamsboard/__init__.py
dreamsboard/agent/REACT_简历任务提取.ipynb
dreamsboard/agent/__init__.py
dreamsboard/agent/convert_llama_index_jsonl_to_llama_factory.py
dreamsboard/agent/eval_questions_48q.txt
dreamsboard/agent/finetuning_events_192q.json
dreamsboard/agent/finetuning_events_192q.jsonl
dreamsboard/agent/gemini_eval_questions_288q.txt
dreamsboard/agent/gemini_eval_questions_48q.txt
dreamsboard/agent/gemini_finetuning_events_168q.jsonl
dreamsboard/agent/gemini_finetuning_events_220q_1710172216.2676702.jsonl
dreamsboard/agent/gemini_q_glm_a_finetuning_events_1152q_1710191088.258371.json
dreamsboard/agent/gemini_q_glm_a_finetuning_events_1152q_1710191088.258371.jsonl
dreamsboard/agent/gemini_questions_360q.txt
dreamsboard/agent/gemini_train_questions_1152q.txt
dreamsboard/agent/gemini_train_questions_192q.txt
dreamsboard/agent/geminifinetuning_events_192q.json
dreamsboard/agent/gen_agent_finetuning.py
dreamsboard/agent/gen_train_questions.py
dreamsboard/agent/glm_eval_questions_288q.txt
dreamsboard/agent/glm_q_gemini_a_finetuning_events_0q_1710251602.6634.jsonl
dreamsboard/agent/glm_q_gemini_a_finetuning_events_0q_1710251716.9279356.jsonl
dreamsboard/agent/glm_q_gemini_a_finetuning_events_0q_1710251894.251382.jsonl
dreamsboard/agent/glm_q_gemini_a_finetuning_events_0q_1710251961.6617868.jsonl
dreamsboard/agent/glm_q_gemini_a_finetuning_events_0q_1710252096.3275669.jsonl
dreamsboard/agent/glm_q_gemini_a_finetuning_events_0q_1710252178.6596577.jsonl
dreamsboard/agent/glm_q_gemini_a_finetuning_events_0q_1710252260.2858505.jsonl
dreamsboard/agent/glm_q_gemini_a_finetuning_events_0q_1710252499.3177001.jsonl
dreamsboard/agent/glm_q_gemini_a_finetuning_events_0q_1710254319.7411973.jsonl
dreamsboard/agent/glm_q_gemini_a_finetuning_events_0q_1717232262.8204503.jsonl
dreamsboard/agent/glm_q_gemini_a_finetuning_events_10q_1710252348.8029423.jsonl
dreamsboard/agent/glm_q_gemini_a_finetuning_events_10q_1710252636.5493147.jsonl
dreamsboard-0.4.0.dist-info/METADATA
dreamsboard-0.4.0.dist-info/WHEEL
dreamsboard-0.4.0.dist-info/entry_points.txt
dreamsboard-0.4.0.dist-info/RECORD
