Metadata-Version: 2.1
Name: dreamsboard
Version: 0.4.0
Summary: 
Author: glide-the
Author-email: 2533736852@qq.com
Requires-Python: >=3.10,<4.0
Classifier: Programming Language :: Python :: 3
Classifier: Programming Language :: Python :: 3.10
Classifier: Programming Language :: Python :: 3.11
Classifier: Programming Language :: Python :: 3.12
Classifier: Programming Language :: Python :: 3.13
Provides-Extra: vector
Requires-Dist: Jinja2 (>=3.1.2,<4.0.0)
Requires-Dist: SQLAlchemy (>=2.0.25,<2.1.0) ; extra == "vector"
Requires-Dist: einops (>=0.8.0,<0.9.0) ; extra == "vector"
Requires-Dist: faiss-cpu (>=1.7.4,<1.8.0) ; extra == "vector"
Requires-Dist: fastapi (>=0.108,<0.109)
Requires-Dist: fsspec (==2023.12.2)
Requires-Dist: json-repair (>=0.26.0,<0.27.0)
Requires-Dist: kor (==1.0.1)
Requires-Dist: langchain (>=0.1.4,<0.2.0)
Requires-Dist: langchain-community (>=0.0.30,<0.0.31)
Requires-Dist: langchain-openai (>=0.0.5,<0.0.6)
Requires-Dist: openapi-pydantic (==0.3.2)
Requires-Dist: orjson (>=3.9.10,<4.0.0)
Requires-Dist: requests (>=2,<3)
Requires-Dist: sentence-transformers (>=3.3.1,<3.4.0) ; extra == "vector"
Requires-Dist: tiktoken (==0.5.2)
Requires-Dist: uvicorn (==0.25.0)
